MANIFEST.in
README.rst
setup.py
docs/HISTORY.txt
docs/LICENSE.GPL
docs/LICENSE.txt
ftw/__init__.py
ftw.chameleon.egg-info/PKG-INFO
ftw.chameleon.egg-info/SOURCES.txt
ftw.chameleon.egg-info/dependency_links.txt
ftw.chameleon.egg-info/entry_points.txt
ftw.chameleon.egg-info/namespace_packages.txt
ftw.chameleon.egg-info/not-zip-safe
ftw.chameleon.egg-info/requires.txt
ftw.chameleon.egg-info/top_level.txt
ftw/chameleon/__init__.py
ftw/chameleon/config.py
ftw/chameleon/configure.zcml
ftw/chameleon/cook_warning.py
ftw/chameleon/events.py
ftw/chameleon/exceptions.py
ftw/chameleon/interfaces.py
ftw/chameleon/patches.py
ftw/chameleon/precook.py
ftw/chameleon/progresslogger.py
ftw/chameleon/testing.py
ftw/chameleon/utils.py
ftw/chameleon/tests/__init__.py
ftw/chameleon/tests/test_cook_warning.py
ftw/chameleon/tests/test_events.py
ftw/chameleon/tests/test_precook.py
ftw/chameleon/tests/test_progresslogger.py
ftw/chameleon/tests/test_utils.py
ftw/chameleon/tests/test_zope_pt_reload.py
ftw/chameleon/tests/templates/foo.pt