Metadata-Version: 1.1
Name: ftw.chameleon
Version: 1.2.0
Summary: Enhance Chameleon templating engine integration into Plone
Home-page: https://github.com/4teamwork/ftw.chameleon
Author: 4teamwork AG
Author-email: mailto:info@4teamwork.ch
License: GPL2
Keywords: ftw chameleon
Platform: UNKNOWN
Classifier: Framework :: Plone
Classifier: Framework :: Plone :: 4.3
Classifier: License :: OSI Approved :: GNU General Public License (GPL)
Classifier: Programming Language :: Python
Classifier: Programming Language :: Python :: 2.7
Classifier: Topic :: Software Development :: Libraries :: Python Modules
